render9/__init__.py
render9/functions.py
render9-0.0.117.dist-info/METADATA
render9-0.0.117.dist-info/WHEEL
render9-0.0.117.dist-info/top_level.txt
render9-0.0.117.dist-info/RECORD
