Metadata-Version: 2.1
Name: render9
Version: 0.0.117
Summary: Render9 OTP is a lightweight and easy-to-use Python package for sending OTP messages via the Render9 OTP API.
Home-page: UNKNOWN
License: UNKNOWN
Platform: UNKNOWN
Requires-Dist: requests
Requires-Dist: python-dotenv
